s3bucketencryptor.py
s3bucketencryptor-0.1.1.dist-info/entry_points.txt
s3bucketencryptor-0.1.1.dist-info/WHEEL
s3bucketencryptor-0.1.1.dist-info/METADATA
s3bucketencryptor-0.1.1.dist-info/RECORD
